{
  "id": "if-vs-when-quiz-1",
  "title": "If vs When",
  "level": "B1",
  "items": [
    {
      "question": "___ the sun goes down, it gets cold here. (certain)",
      "options": ["When", "If", "Unless", "Whether"],
      "answer": 0,
      "explanations": [
        "Correct! The sun definitely goes down, so 'when'.",
        "'If' suggests it might not happen.",
        "'Unless' means 'if not'.",
        "'Whether' introduces a choice, not this time clause."
      ]
    },
    {
      "question": "___ it rains tomorrow, we'll cancel the picnic. (uncertain)",
      "options": ["If", "When", "As", "Once"],
      "answer": 0,
      "explanations": [
        "Correct! Rain is uncertain, so 'if'.",
        "'When' would suggest rain is certain.",
        "'As' doesn't fit this condition.",
        "'Once' suggests it will definitely happen."
      ]
    },
    {
      "question": "I'll call you ___ I get to the airport. (certain arrival)",
      "options": ["when", "if", "unless", "whether"],
      "answer": 0,
      "explanations": [
        "Correct! You will arrive, so 'when I get to the airport'.",
        "'If' would suggest you might not arrive.",
        "'Unless' means 'if not'.",
        "'Whether' introduces a choice."
      ]
    },
    {
      "question": "___ you need anything, just let me know. (possible)",
      "options": ["If", "When", "As soon as", "Once"],
      "answer": 0,
      "explanations": [
        "Correct! Needing something is a possibility, so 'if'.",
        "'When' would suggest it's certain you'll need something.",
        "'As soon as' implies it will happen.",
        "'Once' implies it will happen."
      ]
    },
    {
      "question": "Choose the present simple: 'When it ___ , I'll open the window.'",
      "options": ["gets hot", "will get hot", "is getting hot", "got hot"],
      "answer": 0,
      "explanations": [
        "Correct! Use the present simple after 'when': 'when it gets hot'.",
        "Don't use 'will' after 'when'.",
        "The continuous doesn't fit here.",
        "The past simple doesn't fit a future 'when'."
      ]
    },
    {
      "question": "We'll move to a bigger house ___ the baby is born. (certain)",
      "options": ["when", "if", "unless", "in case"],
      "answer": 0,
      "explanations": [
        "Correct! The baby will be born, so 'when'.",
        "'If' would suggest doubt about the birth.",
        "'Unless' means 'if not'.",
        "'In case' is a precaution, not this time clause."
      ]
    },
    {
      "question": "___ I win the competition, I'll be amazed. (unlikely)",
      "options": ["If", "When", "As soon as", "Once"],
      "answer": 0,
      "explanations": [
        "Correct! Winning is unlikely/uncertain, so 'if'.",
        "'When' would treat winning as certain.",
        "'As soon as' treats it as certain.",
        "'Once' treats it as certain."
      ]
    },
    {
      "question": "___ I drink coffee late, I can't sleep. (a general pattern)",
      "options": ["When", "If only", "Unless", "In case"],
      "answer": 0,
      "explanations": [
        "Correct! 'When' = 'whenever' for a repeated pattern.",
        "'If only' expresses a wish.",
        "'Unless' means 'if not'.",
        "'In case' is a precaution."
      ]
    },
    {
      "question": "Correct this: 'When I will finish work, I'll come over.'",
      "options": [
        "When I finish work, I'll come over.",
        "When I will finish work, I'll come over.",
        "If I will finish work, I'll come over.",
        "When I finishing work, I'll come over."
      ],
      "answer": 0,
      "explanations": [
        "Correct! Use the present simple after 'when': 'When I finish work'.",
        "Don't use 'will' after 'when'.",
        "'If I will' is also wrong, and 'if' changes the meaning.",
        "'When I finishing' uses the wrong form."
      ]
    },
    {
      "question": "Which word shows the event is CERTAIN, only the time is unknown?",
      "options": ["when", "if", "unless", "whether"],
      "answer": 0,
      "explanations": [
        "Correct! 'When' = it will happen; only the timing is open.",
        "'If' shows a possibility that may not happen.",
        "'Unless' means 'if not'.",
        "'Whether' introduces a choice."
      ]
    }
  ]
}
