{
  "id": "on-time-vs-in-time-quiz-1",
  "title": "On time vs In time",
  "level": "B1",
  "items": [
    {
      "question": "The 9:00 train left exactly ___ .",
      "options": ["on time", "in time", "at time", "in the time"],
      "answer": 0,
      "explanations": [
        "Correct! Punctual = 'on time'.",
        "'In time' means early enough, not punctual.",
        "'At time' is not correct.",
        "'In the time' is not correct here."
      ]
    },
    {
      "question": "We ran to the platform and got there just ___ to catch it.",
      "options": ["in time", "on time", "at time", "by time"],
      "answer": 0,
      "explanations": [
        "Correct! Early enough, not too late = 'in time'.",
        "'On time' means punctual, not 'just before it was too late'.",
        "'At time' is not correct.",
        "'By time' is not correct."
      ]
    },
    {
      "question": "Please be ___ for the meeting; it starts at ten sharp.",
      "options": ["on time", "in time", "at time", "in the time"],
      "answer": 0,
      "explanations": [
        "Correct! Punctual = 'on time'.",
        "'In time' means early enough, a slightly different idea.",
        "'At time' is not correct.",
        "'In the time' is not correct."
      ]
    },
    {
      "question": "There's a big surprise ___ of the film.",
      "options": ["at the end", "in the end", "at end", "on the end"],
      "answer": 0,
      "explanations": [
        "Correct! The finishing point takes 'at the end of'.",
        "'In the end' means 'finally', not a place in the film.",
        "'At end' is missing 'the'.",
        "'On the end' is not correct."
      ]
    },
    {
      "question": "We looked at many houses and ___ we bought the first one.",
      "options": ["in the end", "at the end", "on the end", "at end"],
      "answer": 0,
      "explanations": [
        "Correct! 'Finally' = 'in the end'.",
        "'At the end' points to a finishing point, not 'finally'.",
        "'On the end' is not correct.",
        "'At end' is missing 'the'."
      ]
    },
    {
      "question": "I arrived ___ to say goodbye before she left.",
      "options": ["in time", "on time", "at time", "in the end"],
      "answer": 0,
      "explanations": [
        "Correct! Early enough, before it was too late = 'in time'.",
        "'On time' means punctual to a schedule.",
        "'At time' is not correct.",
        "'In the end' means finally."
      ]
    },
    {
      "question": "The bus is never ___ ; it's always five minutes late.",
      "options": ["on time", "in time", "at time", "in the time"],
      "answer": 0,
      "explanations": [
        "Correct! Punctual = 'on time'.",
        "'In time' means early enough, a different idea.",
        "'At time' is not correct.",
        "'In the time' is not correct."
      ]
    },
    {
      "question": "___ of the street, turn left.",
      "options": ["At the end", "In the end", "On the end", "At end"],
      "answer": 0,
      "explanations": [
        "Correct! A place/finishing point takes 'At the end of'.",
        "'In the end' means finally.",
        "'On the end' is not correct.",
        "'At end' is missing 'the'."
      ]
    },
    {
      "question": "Correct this: 'We got to the airport on time to catch the last flight.'",
      "options": [
        "We got to the airport in time to catch the last flight.",
        "We got to the airport on time to catch the last flight.",
        "We got to the airport at time to catch the last flight.",
        "The sentence is already correct."
      ],
      "answer": 0,
      "explanations": [
        "Correct! 'Early enough' = 'in time to catch it'.",
        "'On time' means punctual to a schedule, not this meaning.",
        "'At time' is not correct.",
        "The original uses 'on time' where 'in time' is needed."
      ]
    },
    {
      "question": "What does 'in time' mean?",
      "options": [
        "Early enough, before it's too late.",
        "Exactly at the scheduled time.",
        "Finally, after everything.",
        "At the finishing point."
      ],
      "answer": 0,
      "explanations": [
        "Correct! 'In time' = early enough.",
        "That's 'on time' (punctual).",
        "That's 'in the end' (finally).",
        "That's 'at the end' (the finishing point)."
      ]
    }
  ]
}
